pinax/__init__.py
pinax/wiki/__init__.py
pinax/wiki/apps.py
pinax/wiki/binders.py
pinax/wiki/conf.py
pinax/wiki/forms.py
pinax/wiki/hooks.py
pinax/wiki/models.py
pinax/wiki/parsers.py
pinax/wiki/receivers.py
pinax/wiki/urls.py
pinax/wiki/utils.py
pinax/wiki/views.py
pinax/wiki/migrations/0001_initial.py
pinax/wiki/migrations/__init__.py
pinax/wiki/templatetags/__init__.py
pinax/wiki/templatetags/pinax_wiki_tags.py
pinax/wiki/tests/__init__.py
pinax/wiki/tests/tests.py
pinax/wiki/tests/urls.py
pinax_wiki-2.0.0.dist-info/AUTHORS
pinax_wiki-2.0.0.dist-info/LICENSE
pinax_wiki-2.0.0.dist-info/METADATA
pinax_wiki-2.0.0.dist-info/WHEEL
pinax_wiki-2.0.0.dist-info/top_level.txt
pinax_wiki-2.0.0.dist-info/RECORD
